README.rst
setup.cfg
setup.py
gittyleaks/__init__.py
gittyleaks/__main__.py
gittyleaks/gittyleaks.py
gittyleaks.egg-info/PKG-INFO
gittyleaks.egg-info/SOURCES.txt
gittyleaks.egg-info/dependency_links.txt
gittyleaks.egg-info/entry_points.txt
gittyleaks.egg-info/not-zip-safe
gittyleaks.egg-info/requires.txt
gittyleaks.egg-info/top_level.txt