Metadata-Version: 1.0
Name: gittyleaks
Version: 0.0.17
Summary: Discover where your sensitive data has been leaked.
Home-page: https://github.com/kootenpv/gittyleaks
Author: Pascal van Kooten
Author-email: kootenpv@gmail.com
License: GPL
Platform: UNKNOWN
